ysdb/__init__.py
ysdb/k2a_requests.py
ysdb/wrapper.py
ysdb/ysdbLib.py
ysdb/centos/__init__.py
ysdb/centos/libGL.so.1
ysdb/centos/libGLX.so.0
ysdb/centos/libGLdispatch.so.0
ysdb/centos/libIce++11.so.36
ysdb/centos/libIce.so.36
ysdb/centos/libIceUtil++11.so.36
ysdb/centos/libIceUtil.so.36
ysdb/centos/libQt5Core.so.5
ysdb/centos/libQt5Network.so.5
ysdb/centos/libQt5Test.so.5
ysdb/centos/libQt5X11Extras.so.5
ysdb/centos/libQt5XcbQpa.so.5
ysdb/centos/libX11.so.6
ysdb/centos/libXau.so.6
ysdb/centos/libXext.so.6
ysdb/centos/libicudata.so.56
ysdb/centos/libicui18n.so.56
ysdb/centos/libicuuc.so.56
ysdb/centos/libxcb.so.1
ysdb/centos/libysLib.so
ysdb/centos/libysLib.so.1
ysdb/centos/libysdbLib.so
ysdb/centos/libysdbLib.so.1
ysdb/debian/__init__.py
ysdb/debian/libIce.so.35
ysdb/debian/libIceUtil.so.35
ysdb/debian/libQt5Core.so.5
ysdb/debian/libQt5Network.so.5
ysdb/debian/libQt5Test.so.5
ysdb/debian/libicudata.so.56
ysdb/debian/libicui18n.so.56
ysdb/debian/libicuuc.so.56
ysdb/debian/libysLib.so
ysdb/debian/libysLib.so.1
ysdb/debian/libysdbLib.so
ysdb/debian/libysdbLib.so.1
ysdb/win/Qt5CLucene.dll
ysdb/win/Qt5Concurrent.dll
ysdb/win/Qt5Core.dll
ysdb/win/Qt5DBus.dll
ysdb/win/Qt5Help.dll
ysdb/win/Qt5Network.dll
ysdb/win/Qt5Script.dll
ysdb/win/Qt5Test.dll
ysdb/win/__init__.py
ysdb/win/bzip2.dll
ysdb/win/ice35.dll
ysdb/win/iceutil35.dll
ysdb/win/msvcp120.dll
ysdb/win/msvcr120.dll
ysdb/win/ysLib.dll
ysdb/win/ysdbLib.dll
ysdb/win/zlib.dll
ysdb/win/zlib1.dll
ysdb-0.2.1.dist-info/METADATA
ysdb-0.2.1.dist-info/WHEEL
ysdb-0.2.1.dist-info/top_level.txt
ysdb-0.2.1.dist-info/RECORD
