Metadata-Version: 2.1
Name: ysdb
Version: 0.2.1
Summary: YSDB Python Client SDK
Home-page: https://www.k2data.com.cn
Author: ysdb
Author-email: ysdb@k2data.com.cn
Classifier: Development Status :: 3 - Alpha
Classifier: Intended Audience :: Developers
Classifier: Programming Language :: Python :: 3
Classifier: Programming Language :: Python :: 3.7
Classifier: Programming Language :: Python :: 3.8
Classifier: Programming Language :: Python :: 3.9
Classifier: Programming Language :: Python :: 3.10
Classifier: Operating System :: OS Independent
Classifier: Topic :: Software Development :: Libraries
Requires-Python: >=3.7
Requires-Dist: distro
